odoo8_addon_stock_picking_backorder_to_sale-8.0.1.0.0.99.dev4-nspkg.pth
odoo_addons/stock_picking_backorder_to_sale/README.rst
odoo_addons/stock_picking_backorder_to_sale/__init__.py
odoo_addons/stock_picking_backorder_to_sale/__openerp__.py
odoo_addons/stock_picking_backorder_to_sale/i18n/de.po
odoo_addons/stock_picking_backorder_to_sale/i18n/es.po
odoo_addons/stock_picking_backorder_to_sale/i18n/es_AR.po
odoo_addons/stock_picking_backorder_to_sale/i18n/fi.po
odoo_addons/stock_picking_backorder_to_sale/i18n/fr.po
odoo_addons/stock_picking_backorder_to_sale/i18n/it.po
odoo_addons/stock_picking_backorder_to_sale/i18n/nl.po
odoo_addons/stock_picking_backorder_to_sale/i18n/pt_BR.po
odoo_addons/stock_picking_backorder_to_sale/i18n/ro.po
odoo_addons/stock_picking_backorder_to_sale/i18n/sl.po
odoo_addons/stock_picking_backorder_to_sale/i18n/stock_picking_backorder_to_sale.pot
odoo_addons/stock_picking_backorder_to_sale/i18n/tr.po
odoo_addons/stock_picking_backorder_to_sale/i18n/tr_TR.po
odoo_addons/stock_picking_backorder_to_sale/models/__init__.py
odoo_addons/stock_picking_backorder_to_sale/models/stock.py
odoo_addons/stock_picking_backorder_to_sale/static/description/icon.png
odoo_addons/stock_picking_backorder_to_sale/tests/__init__.py
odoo_addons/stock_picking_backorder_to_sale/tests/test_stock_picking_backorder_to_sale.py
odoo_addons/stock_picking_backorder_to_sale/views/stock_view.xml
odoo8_addon_stock_picking_backorder_to_sale-8.0.1.0.0.99.dev4.dist-info/METADATA
odoo8_addon_stock_picking_backorder_to_sale-8.0.1.0.0.99.dev4.dist-info/WHEEL
odoo8_addon_stock_picking_backorder_to_sale-8.0.1.0.0.99.dev4.dist-info/namespace_packages.txt
odoo8_addon_stock_picking_backorder_to_sale-8.0.1.0.0.99.dev4.dist-info/top_level.txt
odoo8_addon_stock_picking_backorder_to_sale-8.0.1.0.0.99.dev4.dist-info/RECORD
